__builtins__.pyi
_onewire.pyi
binascii.pyi
cmath.pyi
deflate.pyi
dht.pyi
errno.pyi
framebuf.pyi
gc.pyi
hashlib.pyi
heapq.pyi
lcd160cr.pyi
machine.pyi
math.pyi
micropython.pyi
network.pyi
onewire.pyi
platform.pyi
pyb.pyi
random.pyi
select.pyi
socket.pyi
stm.pyi
time.pyi
uarray.pyi
uasyncio.pyi
ubinascii.pyi
ubluetooth.pyi
ucollections.pyi
ucryptolib.pyi
uctypes.pyi
uerrno.pyi
uhashlib.pyi
uheapq.pyi
uio.pyi
ujson.pyi
umachine.pyi
uos.pyi
uplatform.pyi
urandom.pyi
ure.pyi
uselect.pyi
usocket.pyi
ussl.pyi
ustruct.pyi
usys.pyi
utime.pyi
uwebsocket.pyi
uzlib.pyi
vfs.pyi
micropython_stm32_pybv11_stubs-1.27.0.post1.dist-info/LICENSE.md
micropython_stm32_pybv11_stubs-1.27.0.post1.dist-info/METADATA
micropython_stm32_pybv11_stubs-1.27.0.post1.dist-info/WHEEL
micropython_stm32_pybv11_stubs-1.27.0.post1.dist-info/RECORD
